[
    {
        "name": "tile1",
        "cx": 4881600.0,
        "cy": 3917000.0
    },
    {
        "name": "tile2",
        "cx": 4883600.0,
        "cy": 3917000.0
    },
    {
        "name": "tile3",
        "cx": 4885600.0,
        "cy": 3917000.0
    },
    {
        "name": "tile4",
        "cx": 4887600.0,
        "cy": 3917000.0
    },
    {
        "name": "tile5",
        "cx": 4889600.0,
        "cy": 3917000.0
    },
    {
        "name": "tile6",
        "cx": 4891600.0,
        "cy": 3917000.0
    },
    {
        "name": "tile7",
        "cx": 4893600.0,
        "cy": 3917000.0
    },
    {
        "name": "tile8",
        "cx": 4895600.0,
        "cy": 3917000.0
    },
    {
        "name": "tile9",
        "cx": 4897600.0,
        "cy": 3917000.0
    },
    {
        "name": "tile10",
        "cx": 4899600.0,
        "cy": 3917000.0
    },
    {
        "name": "tile11",
        "cx": 4881600.0,
        "cy": 3919000.0
    },
    {
        "name": "tile12",
        "cx": 4883600.0,
        "cy": 3919000.0
    },
    {
        "name": "tile13",
        "cx": 4885600.0,
        "cy": 3919000.0
    },
    {
        "name": "tile14",
        "cx": 4887600.0,
        "cy": 3919000.0
    },
    {
        "name": "tile15",
        "cx": 4889600.0,
        "cy": 3919000.0
    },
    {
        "name": "tile16",
        "cx": 4891600.0,
        "cy": 3919000.0
    },
    {
        "name": "tile17",
        "cx": 4893600.0,
        "cy": 3919000.0
    },
    {
        "name": "tile18",
        "cx": 4895600.0,
        "cy": 3919000.0
    },
    {
        "name": "tile19",
        "cx": 4897600.0,
        "cy": 3919000.0
    },
    {
        "name": "tile20",
        "cx": 4899600.0,
        "cy": 3919000.0
    },
    {
        "name": "tile21",
        "cx": 4881600.0,
        "cy": 3921000.0
    },
    {
        "name": "tile22",
        "cx": 4883600.0,
        "cy": 3921000.0
    },
    {
        "name": "tile23",
        "cx": 4885600.0,
        "cy": 3921000.0
    },
    {
        "name": "tile24",
        "cx": 4887600.0,
        "cy": 3921000.0
    },
    {
        "name": "tile25",
        "cx": 4889600.0,
        "cy": 3921000.0
    },
    {
        "name": "tile26",
        "cx": 4891600.0,
        "cy": 3921000.0
    },
    {
        "name": "tile27",
        "cx": 4893600.0,
        "cy": 3921000.0
    },
    {
        "name": "tile28",
        "cx": 4895600.0,
        "cy": 3921000.0
    },
    {
        "name": "tile29",
        "cx": 4897600.0,
        "cy": 3921000.0
    },
    {
        "name": "tile30",
        "cx": 4899600.0,
        "cy": 3921000.0
    },
    {
        "name": "tile31",
        "cx": 4881600.0,
        "cy": 3923000.0
    },
    {
        "name": "tile32",
        "cx": 4883600.0,
        "cy": 3923000.0
    },
    {
        "name": "tile33",
        "cx": 4885600.0,
        "cy": 3923000.0
    },
    {
        "name": "tile34",
        "cx": 4887600.0,
        "cy": 3923000.0
    },
    {
        "name": "tile35",
        "cx": 4889600.0,
        "cy": 3923000.0
    },
    {
        "name": "tile36",
        "cx": 4891600.0,
        "cy": 3923000.0
    },
    {
        "name": "tile37",
        "cx": 4893600.0,
        "cy": 3923000.0
    },
    {
        "name": "tile38",
        "cx": 4895600.0,
        "cy": 3923000.0
    },
    {
        "name": "tile39",
        "cx": 4897600.0,
        "cy": 3923000.0
    },
    {
        "name": "tile40",
        "cx": 4899600.0,
        "cy": 3923000.0
    },
    {
        "name": "tile41",
        "cx": 4881600.0,
        "cy": 3925000.0
    },
    {
        "name": "tile42",
        "cx": 4883600.0,
        "cy": 3925000.0
    },
    {
        "name": "tile43",
        "cx": 4885600.0,
        "cy": 3925000.0
    },
    {
        "name": "tile44",
        "cx": 4887600.0,
        "cy": 3925000.0
    },
    {
        "name": "tile45",
        "cx": 4889600.0,
        "cy": 3925000.0
    },
    {
        "name": "tile46",
        "cx": 4891600.0,
        "cy": 3925000.0
    },
    {
        "name": "tile47",
        "cx": 4893600.0,
        "cy": 3925000.0
    },
    {
        "name": "tile48",
        "cx": 4895600.0,
        "cy": 3925000.0
    },
    {
        "name": "tile49",
        "cx": 4897600.0,
        "cy": 3925000.0
    },
    {
        "name": "tile50",
        "cx": 4899600.0,
        "cy": 3925000.0
    },
    {
        "name": "tile51",
        "cx": 4881600.0,
        "cy": 3927000.0
    },
    {
        "name": "tile52",
        "cx": 4883600.0,
        "cy": 3927000.0
    },
    {
        "name": "tile53",
        "cx": 4885600.0,
        "cy": 3927000.0
    },
    {
        "name": "tile54",
        "cx": 4887600.0,
        "cy": 3927000.0
    },
    {
        "name": "tile55",
        "cx": 4889600.0,
        "cy": 3927000.0
    },
    {
        "name": "tile56",
        "cx": 4891600.0,
        "cy": 3927000.0
    },
    {
        "name": "tile57",
        "cx": 4893600.0,
        "cy": 3927000.0
    },
    {
        "name": "tile58",
        "cx": 4895600.0,
        "cy": 3927000.0
    },
    {
        "name": "tile59",
        "cx": 4897600.0,
        "cy": 3927000.0
    },
    {
        "name": "tile60",
        "cx": 4899600.0,
        "cy": 3927000.0
    },
    {
        "name": "tile61",
        "cx": 4881600.0,
        "cy": 3929000.0
    },
    {
        "name": "tile62",
        "cx": 4883600.0,
        "cy": 3929000.0
    },
    {
        "name": "tile63",
        "cx": 4885600.0,
        "cy": 3929000.0
    },
    {
        "name": "tile64",
        "cx": 4887600.0,
        "cy": 3929000.0
    },
    {
        "name": "tile65",
        "cx": 4889600.0,
        "cy": 3929000.0
    },
    {
        "name": "tile66",
        "cx": 4891600.0,
        "cy": 3929000.0
    },
    {
        "name": "tile67",
        "cx": 4893600.0,
        "cy": 3929000.0
    },
    {
        "name": "tile68",
        "cx": 4895600.0,
        "cy": 3929000.0
    },
    {
        "name": "tile69",
        "cx": 4897600.0,
        "cy": 3929000.0
    },
    {
        "name": "tile70",
        "cx": 4899600.0,
        "cy": 3929000.0
    },
    {
        "name": "tile71",
        "cx": 4881600.0,
        "cy": 3931000.0
    },
    {
        "name": "tile72",
        "cx": 4883600.0,
        "cy": 3931000.0
    },
    {
        "name": "tile73",
        "cx": 4885600.0,
        "cy": 3931000.0
    },
    {
        "name": "tile74",
        "cx": 4887600.0,
        "cy": 3931000.0
    },
    {
        "name": "tile75",
        "cx": 4889600.0,
        "cy": 3931000.0
    },
    {
        "name": "tile76",
        "cx": 4891600.0,
        "cy": 3931000.0
    },
    {
        "name": "tile77",
        "cx": 4893600.0,
        "cy": 3931000.0
    },
    {
        "name": "tile78",
        "cx": 4895600.0,
        "cy": 3931000.0
    },
    {
        "name": "tile79",
        "cx": 4897600.0,
        "cy": 3931000.0
    },
    {
        "name": "tile80",
        "cx": 4899600.0,
        "cy": 3931000.0
    },
    {
        "name": "tile81",
        "cx": 4881600.0,
        "cy": 3933000.0
    },
    {
        "name": "tile82",
        "cx": 4883600.0,
        "cy": 3933000.0
    },
    {
        "name": "tile83",
        "cx": 4885600.0,
        "cy": 3933000.0
    },
    {
        "name": "tile84",
        "cx": 4887600.0,
        "cy": 3933000.0
    },
    {
        "name": "tile85",
        "cx": 4889600.0,
        "cy": 3933000.0
    },
    {
        "name": "tile86",
        "cx": 4891600.0,
        "cy": 3933000.0
    },
    {
        "name": "tile87",
        "cx": 4893600.0,
        "cy": 3933000.0
    },
    {
        "name": "tile88",
        "cx": 4895600.0,
        "cy": 3933000.0
    },
    {
        "name": "tile89",
        "cx": 4897600.0,
        "cy": 3933000.0
    },
    {
        "name": "tile90",
        "cx": 4899600.0,
        "cy": 3933000.0
    }
]